{
  "appPageId" : "064ffeed-fb45-4542-805a-ee8067a0271c",
  "componentName" : "siteforce:sldsTwoCol84Layout",
  "dataProviders" : [ ],
  "id" : "6635c361-3741-4414-9360-aa468de8c398",
  "label" : "Question Detail",
  "regions" : [ {
    "components" : [ {
      "componentAttributes" : {
        "bannerText" : "",
        "bannerTextWithKnowledge" : "Explore other <a href=\"javascript:void(0)\" class=\"headlineArticles\">articles</a> and <a href=\"javascript:void(0)\" class=\"headlineDiscussions\">discussions</a> on this topic.",
        "bannerTextWithoutKnowledge" : "Explore other <a href=\"javascript:void(0)\" class=\"headlineDiscussions\">discussions</a> on this topic.",
        "pageType" : "discussion",
        "showSubTopics" : true,
        "title" : "Welcome!",
        "uniqueNameOrId" : "{!recordId}"
      },
      "componentName" : "forceCommunity:headline",
      "id" : "48ca240e-e1e9-4880-a376-b1490595fe19",
      "renderPriority" : "NEUTRAL",
      "renditionMap" : { },
      "type" : "component"
    } ],
    "id" : "4d87b04e-243c-462c-98e8-acf41b052e25",
    "regionName" : "header",
    "type" : "region"
  }, {
    "components" : [ {
      "componentAttributes" : {
        "id" : "{!feedItemId}"
      },
      "componentName" : "forceCommunity:feedItemDetail",
      "id" : "d9f3be21-f7c2-4bc4-9f35-97b8e1e5e308",
      "renderPriority" : "NEUTRAL",
      "renditionMap" : { },
      "type" : "component"
    } ],
    "id" : "536e1ce8-1ca2-46e2-a3d6-5cdc9181200f",
    "regionName" : "content",
    "type" : "region"
  }, {
    "components" : [ {
      "componentAttributes" : {
        "numberOfItems" : 5,
        "showViewCounts" : true,
        "title" : "Related Questions"
      },
      "componentName" : "selfService:similarQuestions",
      "id" : "6c3cf67e-e086-4d09-9b30-27b0164b263b",
      "renderPriority" : "NEUTRAL",
      "renditionMap" : { },
      "type" : "component"
    }, {
      "componentAttributes" : {
        "channel" : "DefaultChannel",
        "title" : ""
      },
      "componentName" : "forceCommunity:recommendations",
      "id" : "305dbb34-915a-4529-88be-e7fc9954193f",
      "renderPriority" : "NEUTRAL",
      "renditionMap" : { },
      "type" : "component"
    }, {
      "componentAttributes" : {
        "numberOfArticles" : 5,
        "title" : "Trending Articles",
        "topicId" : "{!topicId}"
      },
      "componentName" : "selfService:topicTrendingArticles42",
      "id" : "5640cd67-6c94-40e5-9ec1-d28eb88d7fc4",
      "renderPriority" : "NEUTRAL",
      "renditionMap" : { },
      "type" : "component"
    } ],
    "id" : "8f220578-fd16-4fc9-9fb4-b4da1ca3c3e1",
    "regionName" : "sidebar",
    "type" : "region"
  }, {
    "components" : [ {
      "componentAttributes" : {
        "askCommunityLabel" : "Ask a Question",
        "buttonBgColor" : "",
        "buttonBgHoverColor" : "",
        "buttonBorderColor" : "",
        "buttonRadius" : 0,
        "buttonTextColor" : "",
        "buttonTextHoverColor" : "",
        "buttonTwoBgColor" : "",
        "buttonTwoBgHoverColor" : "",
        "buttonTwoBorderColor" : "",
        "buttonTwoRadius" : 0,
        "buttonTwoTextColor" : "",
        "buttonTwoTextHoverColor" : "",
        "confirmationMessage" : "Got it!",
        "contactSupportLabel" : "Contact Support",
        "followUpPromptLabel" : "Can we close your question?",
        "headerLabel" : "Don't see what you're looking for?",
        "isAskFollowPromptEnabled" : true,
        "isIncludeArticlesEnabled" : false,
        "isIncludeDiscussionsEnabled" : true,
        "isInitialSatisfactionPromptEnabled" : true,
        "isPublisherDeflectionEnabled" : true,
        "maxSuggestions" : 5,
        "satisfactionPromptLabel" : "Did we help to answer your question?",
        "showDetails" : false,
        "showTopics" : true
      },
      "componentName" : "siteforce:napiliFooter",
      "id" : "911f00ad-47e8-4c23-86aa-a5d88c13e949",
      "renderPriority" : "NEUTRAL",
      "renditionMap" : { },
      "type" : "component"
    } ],
    "id" : "525b7410-72dd-44c5-b440-26337dddd86d",
    "regionName" : "footer",
    "type" : "region"
  }, {
    "components" : [ {
      "componentAttributes" : {
        "customHeadTags" : "",
        "description" : "",
        "title" : "{!Record.Title}"
      },
      "componentName" : "forceCommunity:seoAssistant",
      "id" : "252256d5-1140-4347-b7ea-404450d34567",
      "renditionMap" : { },
      "type" : "component"
    } ],
    "id" : "40d2fc7a-5a8d-4353-941e-7afe4de49ebe",
    "regionName" : "sfdcHiddenRegion",
    "type" : "region"
  } ],
  "themeLayoutType" : "Inner",
  "type" : "view",
  "viewType" : "feeditem"
}