{
    "DesignerCustomizationType": "Discovery Framework",
    "IsActive": true,
    "IsOmniScriptEmbeddable": false,
    "Name": "MisleadingInformationNote",
    "OmniProcessId": {
        "Name": "Open Account",
        "VlocityDataPackType": "VlocityMatchingKeyObject",
        "VlocityMatchingRecordSourceKey": "OmniProcess/FSC_Sample/Account_Opening_Sample/English",
        "VlocityRecordSObjectType": "OmniProcess"
    },
    "ParentElementId": {
        "Name": "Step2",
        "OmniProcessId": {
            "Name": "Open Account",
            "VlocityDataPackType": "VlocityMatchingKeyObject",
            "VlocityMatchingRecordSourceKey": "OmniProcess/FSC_Sample/Account_Opening_Sample/English",
            "VlocityRecordSObjectType": "OmniProcess"
        },
        "VlocityDataPackType": "VlocityMatchingKeyObject",
        "VlocityMatchingRecordSourceKey": "OmniProcessElement/OmniProcess/FSC_Sample/Account_Opening_Sample/English/Step2",
        "VlocityRecordSObjectType": "OmniProcessElement"
    },
    "ParentElementName": "Step2",
    "ParentElementType": "Step",
    "PropertySetConfig": {
        "HTMLTemplateId": "",
        "controlWidth": 12,
        "dataJSON": false,
        "label": "Note: It is an offence under the applicable regional law to give false or misleading information or documents.",
        "sanitize": false,
        "show": null,
        "text": "Note: It is an offence under the applicable regional law to give false or misleading information or documents.",
        "textKey": ""
    },
    "Type": "Text Block",
    "VlocityDataPackType": "SObject",
    "VlocityRecordSObjectType": "OmniProcessElement",
    "VlocityRecordSourceKey": "OmniProcessElement/OmniProcess/FSC_Sample/Account_Opening_Sample/English/MisleadingInformationNote"
}